songbird/__init__.py
songbird/cli.py
songbird/cli_utils.py
songbird/conversation.py
songbird/orchestrator.py
songbird/version.py
songbird/agent/__init__.py
songbird/agent/agent_core.py
songbird/agent/context_manager.py
songbird/agent/message_classifier.py
songbird/agent/plan_manager.py
songbird/agent/planning.py
songbird/commands/__init__.py
songbird/commands/base.py
songbird/commands/clear_command.py
songbird/commands/file_reference_parser.py
songbird/commands/help_command.py
songbird/commands/input_handler.py
songbird/commands/loader.py
songbird/commands/model_command.py
songbird/commands/prompt_toolkit_input.py
songbird/commands/registry.py
songbird/config/__init__.py
songbird/config/config_manager.py
songbird/config/mapping_loader.py
songbird/config/provider_mapping.toml
songbird/core/__init__.py
songbird/core/event_loop_manager.py
songbird/core/loop_cleanup_patch.py
songbird/core/signal_handler.py
songbird/discovery/__init__.py
songbird/discovery/model_discovery.py
songbird/llm/__init__.py
songbird/llm/aiohttp_session_manager.py
songbird/llm/copilot_provider.py
songbird/llm/http_session_manager.py
songbird/llm/litellm_adapter.py
songbird/llm/providers.py
songbird/llm/types.py
songbird/llm/unified_interface.py
songbird/memory/__init__.py
songbird/memory/history_manager.py
songbird/memory/models.py
songbird/memory/optimized_manager.py
songbird/prompts/__init__.py
songbird/prompts/agent.txt
songbird/tools/__init__.py
songbird/tools/executor.py
songbird/tools/file_operations.py
songbird/tools/file_search.py
songbird/tools/glob_tool.py
songbird/tools/grep_tool.py
songbird/tools/ls_tool.py
songbird/tools/multiedit_tool.py
songbird/tools/semantic_config.py
songbird/tools/semantic_matcher.py
songbird/tools/shell_exec.py
songbird/tools/todo_manager.py
songbird/tools/todo_tools.py
songbird/tools/tool_registry.py
songbird/tools/tool_runner.py
songbird/tools/tree_tool.py
songbird/ui/__init__.py
songbird/ui/data_transfer.py
songbird/ui/ui_layer.py
songbird_ai-0.1.14.1.dist-info/METADATA
songbird_ai-0.1.14.1.dist-info/WHEEL
songbird_ai-0.1.14.1.dist-info/entry_points.txt
songbird_ai-0.1.14.1.dist-info/licenses/LICENSE
songbird_ai-0.1.14.1.dist-info/RECORD
