Metadata-Version: 2.4
Name: songbird-ai
Version: 0.1.14.1
Summary: A terminal-based AI coding companion that runs on local LLMs
Project-URL: Homepage, https://github.com/Spandan7724/songbird
Project-URL: Documentation, https://github.com/Spandan7724/songbird/blob/main/README.md
Project-URL: Repository, https://github.com/Spandan7724/songbird.git
Project-URL: Issues, https://github.com/Spandan7724/songbird/issues
Author: Spandan Chavan
License-Expression: MIT
License-File: LICENSE
Keywords: ai,assistant,cli,coding,llm,terminal
Classifier: Development Status :: 3 - Alpha
Classifier: Environment :: Console
Classifier: Intended Audience :: Developers
Classifier: License :: OSI Approved :: MIT License
Classifier: Operating System :: OS Independent
Classifier: Programming Language :: Python :: 3
Classifier: Programming Language :: Python :: 3.10
Classifier: Programming Language :: Python :: 3.11
Classifier: Programming Language :: Python :: 3.12
Classifier: Topic :: Software Development :: Libraries :: Python Modules
Classifier: Topic :: Utilities
Requires-Python: >=3.10
Requires-Dist: anthropic>=0.45.0
Requires-Dist: appdirs>=1.4.4
Requires-Dist: google-genai>=0.5.0
Requires-Dist: hatch>=1.14.1
Requires-Dist: httpx[http2]>=0.28.0
Requires-Dist: inquirerpy>=0.3.4
Requires-Dist: litellm<2.0,>=1.70
Requires-Dist: ollama>=0.5.1
Requires-Dist: openai>=1.61.0
Requires-Dist: prompt-toolkit>=3.0.51
Requires-Dist: psutil>=5.9.0
Requires-Dist: rich>=13.7.1
Requires-Dist: typer>=0.16.0
Provides-Extra: dev
Requires-Dist: coverage[toml]>=7.9.1; extra == 'dev'
Requires-Dist: httpx>=0.27.0; extra == 'dev'
Requires-Dist: pytest-asyncio>=1.0.0; extra == 'dev'
Requires-Dist: pytest>=8.4.0; extra == 'dev'
